pandoc_glossary_filter/__init__.py
pandoc_glossary_filter/__main__.py
pandoc_glossary_filter/data.py
pandoc_glossary_filter/filter.py
pandoc_glossary_filter-0.4.2.dist-info/entry_points.txt
pandoc_glossary_filter-0.4.2.dist-info/LICENSE
pandoc_glossary_filter-0.4.2.dist-info/WHEEL
pandoc_glossary_filter-0.4.2.dist-info/METADATA
pandoc_glossary_filter-0.4.2.dist-info/RECORD
